Workbook
Name Slicer_Year: #N/A

Sheet Stats

Sheet MonthlyRevenue
A1: Month Date | B1: total_orders | C1: revenue | D1: Year | E1: mom_growth_pct
A2: 42736 | B2: 750 | C2: 111798.36 | D2: 2017 | E2: =IFERROR((MonthlyRevenue[[#This Row],[revenue]]-MonthlyRevenue[[#Headers],[revenue]])/MonthlyRevenue[[#This Row],[revenue]],"")
A3: 42767 | B3: 1653 | C3: 234223.4 | D3: 2017 | E3: =IFERROR((MonthlyRevenue[[#This Row],[revenue]]-C2)/C2,"") -> 1.0950522
A4: 42795 | B4: 2546 | C4: 359198.85 | D4: 2017 | E4: =IFERROR((MonthlyRevenue[[#This Row],[revenue]]-C3)/C3,"") -> 0.53357372
A5: 42826 | B5: 2303 | C5: 340669.68 | D5: 2017 | E5: =IFERROR((MonthlyRevenue[[#This Row],[revenue]]-C4)/C4,"") -> -0.051584714
A6: 42856 | B6: 3546 | C6: 489338.25 | D6: 2017 | E6: =IFERROR((MonthlyRevenue[[#This Row],[revenue]]-C5)/C5,"") -> 0.43640094
A7: 42887 | B7: 3135 | C7: 421923.37 | D7: 2017 | E7: =IFERROR((MonthlyRevenue[[#This Row],[revenue]]-C6)/C6,"") -> -0.13776744
A8: 42917 | B8: 3872 | C8: 481604.52 | D8: 2017 | E8: =IFERROR((MonthlyRevenue[[#This Row],[revenue]]-C7)/C7,"") -> 0.14145021
A9: 42948 | B9: 4193 | C9: 554699.7 | D9: 2017 | E9: =IFERROR((MonthlyRevenue[[#This Row],[revenue]]-C8)/C8,"") -> 0.15177428
A10: 42979 | B10: 4150 | C10: 607399.67 | D10: 2017 | E10: =IFERROR((MonthlyRevenue[[#This Row],[revenue]]-C9)/C9,"") -> 0.095006307
A11: 43009 | B11: 4478 | C11: 648247.65 | D11: 2017 | E11: =IFERROR((MonthlyRevenue[[#This Row],[revenue]]-C10)/C10,"") -> 0.06725058
A12: 43040 | B12: 7289 | C12: 987765.37 | D12: 2017 | E12: =IFERROR((MonthlyRevenue[[#This Row],[revenue]]-C11)/C11,"") -> 0.52374694
A13: 43070 | B13: 5513 | C13: 726033.19 | D13: 2017 | E13: =IFERROR((MonthlyRevenue[[#This Row],[revenue]]-C12)/C12,"") -> -0.26497404
A14: 43101 | B14: 7069 | C14: 924645 | D14: 2018 | E14: =IFERROR((MonthlyRevenue[[#This Row],[revenue]]-C13)/C13,"") -> 0.27355748
... A21: 43313 | B21: 6351 | C21: 838576.64 | D21: 2018 | E21: =IFERROR((MonthlyRevenue[[#This Row],[revenue]]-C20)/C20,"") -> -0.033846077

Sheet Top10Categories
A1: category | B1: orders | C1: revenue | D1: revenue_share_pct | E1: revenue_rank
A2: Health Beauty | B2: 8647 | C2: 1233131.7 | D2: 9.33 | E2: 1
A3: Watches Gifts | B3: 5495 | C3: 1166177 | D3: 8.82 | E3: 2
A4: Bed Bath Table | B4: 9272 | C4: 1023434.8 | D4: 7.74 | E4: 3
A5: Sports Leisure | B5: 7530 | C5: 954852.55 | D5: 7.22 | E5: 4
A6: Computers Accessories | B6: 6530 | C6: 888724.61 | D6: 6.72 | E6: 5
A7: Furniture Decor | B7: 6307 | C7: 711927.69 | D7: 5.38 | E7: 6
A8: Housewares | B8: 5743 | C8: 615628.69 | D8: 4.66 | E8: 7
A9: Cool Stuff | B9: 3559 | C9: 610204.1 | D9: 4.62 | E9: 8
A10: Auto | B10: 3810 | C10: 578966.65 | D10: 4.38 | E10: 9
A11: Toys | B11: 3804 | C11: 471286.48 | D11: 3.56 | E11: 10

Sheet Categories
A1: category | B1: orders | C1: revenue | D1: revenue_share_pct | E1: revenue_rank
A2: Health Beauty | B2: 8647 | C2: 1233131.7 | D2: 9.33 | E2: 1
A3: Watches Gifts | B3: 5495 | C3: 1166177 | D3: 8.82 | E3: 2
A4: Bed Bath Table | B4: 9272 | C4: 1023434.8 | D4: 7.74 | E4: 3
A5: Sports Leisure | B5: 7530 | C5: 954852.55 | D5: 7.22 | E5: 4
A6: Computers Accessories | B6: 6530 | C6: 888724.61 | D6: 6.72 | E6: 5
A7: Furniture Decor | B7: 6307 | C7: 711927.69 | D7: 5.38 | E7: 6
A8: Housewares | B8: 5743 | C8: 615628.69 | D8: 4.66 | E8: 7
A9: Cool Stuff | B9: 3559 | C9: 610204.1 | D9: 4.62 | E9: 8
A10: Auto | B10: 3810 | C10: 578966.65 | D10: 4.38 | E10: 9
A11: Toys | B11: 3804 | C11: 471286.48 | D11: 3.56 | E11: 10
A12: Garden Tools | B12: 3448 | C12: 470495.28 | D12: 3.56 | E12: 11
A13: Baby | B13: 2809 | C13: 400421.84 | D13: 3.03 | E13: 12
... A75: Security And Services | B75: 2 | C75: 283.29 | D75: 0 | E75: 74

Sheet CustomerType
A1: customer_type | B1: customers | C1: revenue | D1: revenue_share_pct | E1: customers_share_pct
A2: One-time | B2: 90557 | C2: 12493089 | D2: 94.49 | E2: =CustomerType[[#This Row],[customers]]/SUM(CustomerType[customers]) -> 0.96999722
A3: Repeat | B3: 2801 | C3: 728408.75 | D3: 5.51 | E3: =CustomerType[[#This Row],[customers]]/SUM(CustomerType[customers]) -> 0.030002785

Sheet Cohort
A1: Cohort Month | B1: M0 | C1: M1 | D1: M2 | E1: M3 | F1: M4 | G1: M5 | H1: M6
A2: 42736 | B2: 717 | C2: 2 | D2: 2 | E2: 1 | F2: 3 | G2: 1 | H2: 3
A3: 42767 | B3: 1628 | C3: 3 | D3: 5 | E3: 2 | F3: 7 | G3: 2 | H3: 4
A4: 42795 | B4: 2503 | C4: 11 | D4: 9 | E4: 10 | F4: 9 | G4: 4 | H4: 4
A5: 42826 | B5: 2256 | C5: 14 | D5: 5 | E5: 4 | F5: 6 | G5: 6 | H5: 8
A6: 42856 | B6: 3451 | C6: 16 | D6: 16 | E6: 10 | F6: 10 | G6: 11 | H6: 14
A7: 42887 | B7: 3037 | C7: 15 | D7: 12 | E7: 13 | F7: 9 | G7: 12 | H7: 11
A8: 42917 | B8: 3752 | C8: 20 | D8: 13 | E8: 9 | F8: 11 | G8: 8 | H8: 12
A9: 42948 | B9: 4057 | C9: 28 | D9: 14 | E9: 11 | F9: 14 | G9: 21 | H9: 12
A10: 42979 | B10: 4004 | C10: 28 | D10: 22 | E10: 11 | F10: 18 | G10: 9 | H10: 9
A11: 43009 | B11: 4328 | C11: 31 | D11: 11 | E11: 4 | F11: 10 | G11: 9 | H11: 9
A12: 43040 | B12: 7060 | C12: 40 | D12: 26 | E12: 12 | F12: 12 | G12: 13 | H12: 8
A13: 43070 | B13: 5338 | C13: 11 | D13: 15 | E13: 18 | F13: 14 | G13: 11 | H13: 9
... A15: 43132 | B15: 6288 | C15: 22 | D15: 25 | E15: 19 | F15: 16 | G15: 14 | H15: 13

Sheet ReviewVsDelivery
A1: review_score | B1: reviews | C1: avg_delivery_days | D1: pct_late
A2: 1 | B2: 9405 | C2: 21.3 | D2: 0.378
A3: 2 | B3: 2941 | C3: 16.6 | D3: 0.206
A4: 3 | B4: 7961 | C4: 14.2 | D4: 0.11
A5: 4 | B5: 18986 | C5: 12.3 | D5: 0.05
A6: 5 | B6: 57059 | C6: 10.6 | D6: 0.03

Sheet Pivots
A1: Row Labels | B1: Sum of revenue
A2: 42736 | B2: 111798.36
A3: 42767 | B3: 234223.4
A4: 42795 | B4: 359198.85
A5: 42826 | B5: 340669.68
A6: 42856 | B6: 489338.25
A7: 42887 | B7: 421923.37
A8: 42917 | B8: 481604.52
A9: 42948 | B9: 554699.7
A10: 42979 | B10: 607399.67
A11: 43009 | B11: 648247.65
A12: 43040 | B12: 987765.37
A13: 43070 | B13: 726033.19
A14: Grand Total | B14: 5962902

Sheet Dashboard
B1: Olist E-Commerce: Sales & Customer Analysis
B3: Total Revenue | E3: Total Orders | H3: Avg Order Value | K3: Unique Customers | N3: Avg Review Score | Q3: Avg Delivery Days
B4: =Calcs!B2 -> 13221498 | E4: =Calcs!B3 -> 96478 | H4: =Calcs!B4 -> 137.04159 | K4: =Calcs!B5 -> 93358 | N4: =Calcs!B6 -> 4.16 | Q4: =Calcs!B7 -> 12.5
J55: Less than 1% of customers buy again in the following months
J57: Cohort | K57: Month 1 | L57: Month 2 | M57: Month 3 | N57: Month 4 | O57: Month 5 | P57: Month 6
J58: ='Cohort'!A2 -> 42736 | K58: ='Cohort'!C2/'Cohort'!$B2 -> 0.0027894003 | L58: ='Cohort'!D2/'Cohort'!$B2 -> 0.0027894003 | M58: ='Cohort'!E2/'Cohort'!$B2 -> 0.0013947001 | N58: ='Cohort'!F2/'Cohort'!$B2 -> 0.0041841004 | O58: ='Cohort'!G2/'Cohort'!$B2 -> 0.0013947001 | P58: ='Cohort'!H2/'Cohort'!$B2 -> 0.0041841004
J59: ='Cohort'!A3 -> 42767 | K59: ='Cohort'!C3/'Cohort'!$B3 -> 0.0018427518 | L59: ='Cohort'!D3/'Cohort'!$B3 -> 0.0030712531 | M59: ='Cohort'!E3/'Cohort'!$B3 -> 0.0012285012 | N59: ='Cohort'!F3/'Cohort'!$B3 -> 0.0042997543 | O59: ='Cohort'!G3/'Cohort'!$B3 -> 0.0012285012 | P59: ='Cohort'!H3/'Cohort'!$B3 -> 0.0024570025
J60: ='Cohort'!A4 -> 42795 | K60: ='Cohort'!C4/'Cohort'!$B4 -> 0.0043947263 | L60: ='Cohort'!D4/'Cohort'!$B4 -> 0.0035956852 | M60: ='Cohort'!E4/'Cohort'!$B4 -> 0.0039952058 | N60: ='Cohort'!F4/'Cohort'!$B4 -> 0.0035956852 | O60: ='Cohort'!G4/'Cohort'!$B4 -> 0.0015980823 | P60: ='Cohort'!H4/'Cohort'!$B4 -> 0.0015980823
J61: ='Cohort'!A5 -> 42826 | K61: ='Cohort'!C5/'Cohort'!$B5 -> 0.0062056738 | L61: ='Cohort'!D5/'Cohort'!$B5 -> 0.0022163121 | M61: ='Cohort'!E5/'Cohort'!$B5 -> 0.0017730496 | N61: ='Cohort'!F5/'Cohort'!$B5 -> 0.0026595745 | O61: ='Cohort'!G5/'Cohort'!$B5 -> 0.0026595745 | P61: ='Cohort'!H5/'Cohort'!$B5 -> 0.0035460993
J62: ='Cohort'!A6 -> 42856 | K62: ='Cohort'!C6/'Cohort'!$B6 -> 0.0046363373 | L62: ='Cohort'!D6/'Cohort'!$B6 -> 0.0046363373 | M62: ='Cohort'!E6/'Cohort'!$B6 -> 0.0028977108 | N62: ='Cohort'!F6/'Cohort'!$B6 -> 0.0028977108 | O62: ='Cohort'!G6/'Cohort'!$B6 -> 0.0031874819 | P62: ='Cohort'!H6/'Cohort'!$B6 -> 0.0040567951
J63: ='Cohort'!A7 -> 42887 | K63: ='Cohort'!C7/'Cohort'!$B7 -> 0.0049390846 | L63: ='Cohort'!D7/'Cohort'!$B7 -> 0.0039512677 | M63: ='Cohort'!E7/'Cohort'!$B7 -> 0.00428054 | N63: ='Cohort'!F7/'Cohort'!$B7 -> 0.0029634508 | O63: ='Cohort'!G7/'Cohort'!$B7 -> 0.0039512677 | P63: ='Cohort'!H7/'Cohort'!$B7 -> 0.0036219954
J64: ='Cohort'!A8 -> 42917 | K64: ='Cohort'!C8/'Cohort'!$B8 -> 0.0053304904 | L64: ='Cohort'!D8/'Cohort'!$B8 -> 0.0034648188 | M64: ='Cohort'!E8/'Cohort'!$B8 -> 0.0023987207 | N64: ='Cohort'!F8/'Cohort'!$B8 -> 0.0029317697 | O64: ='Cohort'!G8/'Cohort'!$B8 -> 0.0021321962 | P64: ='Cohort'!H8/'Cohort'!$B8 -> 0.0031982942
J65: ='Cohort'!A9 -> 42948 | K65: ='Cohort'!C9/'Cohort'!$B9 -> 0.0069016515 | L65: ='Cohort'!D9/'Cohort'!$B9 -> 0.0034508257 | M65: ='Cohort'!E9/'Cohort'!$B9 -> 0.0027113631 | N65: ='Cohort'!F9/'Cohort'!$B9 -> 0.0034508257 | O65: ='Cohort'!G9/'Cohort'!$B9 -> 0.0051762386 | P65: ='Cohort'!H9/'Cohort'!$B9 -> 0.0029578506
J66: ='Cohort'!A10 -> 42979 | K66: ='Cohort'!C10/'Cohort'!$B10 -> 0.006993007 | L66: ='Cohort'!D10/'Cohort'!$B10 -> 0.0054945055 | M66: ='Cohort'!E10/'Cohort'!$B10 -> 0.0027472527 | N66: ='Cohort'!F10/'Cohort'!$B10 -> 0.0044955045 | O66: ='Cohort'!G10/'Cohort'!$B10 -> 0.0022477522 | P66: ='Cohort'!H10/'Cohort'!$B10 -> 0.0022477522
J67: ='Cohort'!A11 -> 43009 | K67: ='Cohort'!C11/'Cohort'!$B11 -> 0.0071626617 | L67: ='Cohort'!D11/'Cohort'!$B11 -> 0.0025415896 | M67: ='Cohort'!E11/'Cohort'!$B11 -> 0.00092421442 | N67: ='Cohort'!F11/'Cohort'!$B11 -> 0.002310536 | O67: ='Cohort'!G11/'Cohort'!$B11 -> 0.0020794824 | P67: ='Cohort'!H11/'Cohort'!$B11 -> 0.0020794824
J68: ='Cohort'!A12 -> 43040 | K68: ='Cohort'!C12/'Cohort'!$B12 -> 0.0056657224 | L68: ='Cohort'!D12/'Cohort'!$B12 -> 0.0036827195 | M68: ='Cohort'!E12/'Cohort'!$B12 -> 0.0016997167 | N68: ='Cohort'!F12/'Cohort'!$B12 -> 0.0016997167 | O68: ='Cohort'!G12/'Cohort'!$B12 -> 0.0018413598 | P68: ='Cohort'!H12/'Cohort'!$B12 -> 0.0011331445
J69: ='Cohort'!A13 -> 43070 | K69: ='Cohort'!C13/'Cohort'!$B13 -> 0.0020606969 | L69: ='Cohort'!D13/'Cohort'!$B13 -> 0.0028100412 | M69: ='Cohort'!E13/'Cohort'!$B13 -> 0.0033720495 | N69: ='Cohort'!F13/'Cohort'!$B13 -> 0.0026227051 | O69: ='Cohort'!G13/'Cohort'!$B13 -> 0.0020606969 | P69: ='Cohort'!H13/'Cohort'!$B13 -> 0.0016860247
... J71: ='Cohort'!A15 -> 43132 | K71: ='Cohort'!C15/'Cohort'!$B15 -> 0.0034987277 | L71: ='Cohort'!D15/'Cohort'!$B15 -> 0.003975827 | M71: ='Cohort'!E15/'Cohort'!$B15 -> 0.0030216285 | N71: ='Cohort'!F15/'Cohort'!$B15 -> 0.0025445293 | O71: ='Cohort'!G15/'Cohort'!$B15 -> 0.0022264631 | P71: ='Cohort'!H15/'Cohort'!$B15 -> 0.00206743
B77: Source: Olist public dataset (Kaggle). Delivered orders only.
B78: Currency: R$. Monthly charts cover Jan 2017 to Aug 2018.

Sheet LateVsOnTime
A1: delivery_status | B1: reviews | C1: avg_review_score | E1: Score gap (on time - late) | F1: Late share of reviews
A2: On time | B2: 88652 | C2: 4.29 | E2: =_04b_late_vs_ontime[[#This Row],[avg_review_score]]-C3 -> 1.72 | F2: =B3/(_04b_late_vs_ontime[[#This Row],[reviews]]+B3) -> 0.079915311
A3: Late | B3: 7700 | C3: 2.57

Sheet StateDelivery
A1: State | B1: customer_state | C1: orders | D1: avg_delivery_days
A2: Roraima | B2: RR | C2: 41 | D2: 29.3
A3: Acre | B3: AC | C3: 80 | D3: 21
A4: Amapá | B4: AP | C4: 67 | D4: 27.2
A5: Alagoas | B5: AL | C5: 397 | D5: 24.5
A6: Amazonas | B6: AM | C6: 145 | D6: 26.4
A7: Pará | B7: PA | C7: 946 | D7: 23.7
A8: Bahia | B8: BA | C8: 3256 | D8: 19.3
A9: Maranhão | B9: MA | C9: 717 | D9: 21.5
A10: Ceará | B10: CE | C10: 1279 | D10: 21.2
A11: Sergipe | B11: SE | C11: 335 | D11: 21.5
A12: Distrito Federal | B12: DF | C12: 2080 | D12: 12.9
A13: Espírito Santo | B13: ES | C13: 1995 | D13: 15.7
... A28: São Paulo | B28: SP | C28: 40494 | D28: 8.7

Sheet Payments
A1: payment_type | B1: orders | C1: total_value | D1: value_share_pct | E1: avg_installments
A2: Credit Card | B2: 74304 | C2: 12101095 | D2: 0.7846 | E2: 3.5
A3: Boleto | B3: 19191 | C3: 2769932.6 | D3: 0.1796 | E3: 1
A4: Voucher | B4: 3679 | C4: 343013.19 | D4: 0.0222 | E4: 1
A5: Debit Card | B5: 1485 | C5: 208421.12 | D5: 0.0135 | E5: 1

Sheet Calcs
A2: Total Revenue | B2: =INDEX(KPIs[Value], MATCH("total_revenue", KPIs[Metric], 0)) -> 13221498
A3: Total Orders | B3: =INDEX(KPIs[Value], MATCH("total_orders", KPIs[Metric], 0)) -> 96478
A4: Avg Order Value | B4: =B2/B3 -> 137.04159
A5: Unique Customers | B5: =INDEX(KPIs[Value], MATCH("unique_customers", KPIs[Metric], 0)) -> 93358
A6: Avg Review Score | B6: =INDEX(KPIs[Value], MATCH("avg_review_score", KPIs[Metric], 0)) -> 4.16
A7: Avg Delivery Days | B7: =INDEX(KPIs[Value], MATCH("avg_delivery_days", KPIs[Metric], 0)) -> 12.5
A8: Repeat Customers % | B8: =INDEX(CustomerType[customers], MATCH("Repeat", CustomerType[customer_type], 0)) / SUM(CustomerType[customers]) -> 0.030002785

Sheet KPIs
A1: Metric | B1: Value
A2: total_orders | B2: 96478
A3: total_revenue | B3: 13221498
A4: unique_customers | B4: 93358
A5: avg_review_score | B5: 4.16
A6: avg_delivery_days | B6: 12.5

Sheet Sheet6

Sheet States
A1: Code | B1: State
A2: AC | B2: Acre
A3: AL | B3: Alagoas
A4: AP | B4: Amapá
A5: AM | B5: Amazonas
A6: BA | B6: Bahia
A7: CE | B7: Ceará
A8: DF | B8: Distrito Federal
A9: ES | B9: Espírito Santo
A10: GO | B10: Goiás
A11: MA | B11: Maranhão
A12: MT | B12: Mato Grosso
... A28: TO | B28: Tocantins
